LICENSE
MANIFEST.in
README.md
setup.py
smother/__init__.py
smother/cli.py
smother/control.py
smother/diff.py
smother/git.py
smother/interval.py
smother/nose_plugin.py
smother/pytest_plugin.py
smother/python.py
smother.egg-info/PKG-INFO
smother.egg-info/SOURCES.txt
smother.egg-info/dependency_links.txt
smother.egg-info/entry_points.txt
smother.egg-info/requires.txt
smother.egg-info/top_level.txt
smother/tests/.smother
smother/tests/.smother_2
smother/tests/.smother_3
smother/tests/__init__.py
smother/tests/demo.py
smother/tests/demo_testsuite.py
smother/tests/test_cli.py
smother/tests/test_controller.py
smother/tests/test_diff.py
smother/tests/test_git.py
smother/tests/test_interval.py
smother/tests/test_plugins.py
smother/tests/test_python.py
smother/tests/utils.py