Metadata-Version: 1.1
Name: smother
Version: 0.2
Summary: An abundance of coverage data
Home-page: https://github.com/chrisbeaumont/smother
Author: Chris Beaumont
Author-email: chrisnbeaumont@gmail.com
License: UNKNOWN
Platform: UNKNOWN
Classifier: Intended Audience :: Developers
Classifier: Operating System :: OS Independent
Classifier: Programming Language :: Python :: 2.7
Classifier: Programming Language :: Python :: 3.3
Classifier: Programming Language :: Python :: 3.4
Classifier: Programming Language :: Python :: 3.5
Classifier: License :: OSI Approved :: MIT License
